task_command_line/__init__.py
task_command_line/__main__.py
task_command_line/colors.py
task_command_line/command_line.py
task_command_line/interface.py
task_command_line-1.0.2.dist-info/METADATA
task_command_line-1.0.2.dist-info/WHEEL
task_command_line-1.0.2.dist-info/entry_points.txt
task_command_line-1.0.2.dist-info/top_level.txt
task_command_line-1.0.2.dist-info/RECORD
