Metadata-Version: 2.2
Name: task-command-line
Version: 1.0.2
Summary: Yet another task manager
Author-email: EasternFarmer <franek.banas1@gmail.com>
Project-URL: Homepage, https://github.com/EasternFarmer/task-cli
Project-URL: Issues, https://github.com/EasternFarmer/task-cli/issues
Classifier: Programming Language :: Python :: 3
Classifier: Operating System :: OS Independent
Requires-Python: >=3.7
Requires-Dist: platformdirs
